{
  "overrides": {
    "Kizer Element 60 Aggressive Frame": 20,
    "Kizer SoulFrame 60": 20,
    "Kizer SoulFrame 68": 20,
    "Kizer Element 80 UFS Frame": 20,
    "Kizer Element II HILO Ti Frame": 20,
    "Kizer Fluid IV Superfluid Frame": 20,
    "Kizer Element II Grindblock": 20,
    "Kizer Fluid V Superfluid Frame": 20,
    "Kizer Fluid V Team Grey Frame": 20,
    "Kizer Edge 80 NT Silver UFS Frame": 20,
    "Kizer Edge 84 NT Silver UFS Frame": 20,
    "Kizer Edge 90 NT Silver UFS Frame": 20,
    "Kizer Bag": 20,
    "Kizer Soulframe 65 White Frame": 20,
    "Kizer Suspension Skeleton White Frame": 20,
    "Kizer Suspension Skeleton Superfluid Frame": 20,
    "Kizer Soulframe 65 Superfluid Frame": 20,
    "Kizer Team Fluid IV Black/White SL Frame": 20,
    "Kizer Team Fluid IV White/Grey SL Frame": 20,
    "Kizer Team Fluid IV White Frame": 20,
    "Kizer Team Fluid IV Black Frame": 20,
    "Kizer Team Fluid V Black/White Frame": 20,
    "Kizer Team Fluid V White/Grey Frame": 20,
    "Kizer Fluid V Team White Frame": 20,
    "Kizer Team Fluid V White Frame": 20,
    "Kizer Team Fluid V Black Frame": 20,
    "Kizer Flat Grindblock Composite (Element & Unlimited)": 20,
    "Kizer Axle Shift Unlimited Grindblock": 20,
    "Kizer Suspension Kit": 20,
    "Kizer SUV 125 Ti, UFS Frame": 20,
    "Kizer Heel Raiser": 20,
    "Kizer AL Memory Buckle": 20,
    "Kizer Edge NT 580 UFS Frame": 20,
    "Kizer Supreme Buckle Set complete White L / R": 20,
    "Rollerblade Crossfire Skates": 70,
    "Rollerblade Revv Boa 110 Skates": 70,
    "USD Transformer Kids Aggressive Skates": 70,
    "USD Aeon 60 Mery Munoz Pro Aggressive Skates": 70,
    "USD Sway Sagona Allstar Aggressive Skates": 70,
    "USD Sway Carlos Bernal Aggressive Skates": 70,
    "USD Sway Team 60 Aggressive Skates": 70,
    "USD Sway 58 XXIV Aggressive Skates": 70,
    "USD Aeon 60 Richie Eisler Aggressive Skates": 70,
    "USD Aeon Bladies Fabiola Da Silva Aggressive Skate": 70,
    "USD Glitch Vikings on Skates Kids Aggressive Skates": 70,
    "USD Aeon Sam Crofts V Aggressive Skates": 70,
    "USD Aeon 80 Sand Aggressive Skates": 70,
    "USD Shadow Team White Aggressive Skates": 70,
    "USD Aeon Team 60 White Aggressive Skate": 70,
    "USD Aeon 60 Black Aggressive Skate": 70,
    "Doop Dusk 90 Skates": 900000,
    "Powerslide Arise SL Skates": 900000,
    "Powerslide Imperial Lollipop 80 Skates": 900000,
    "Powerslide Next Fatmi Pro 100 Skates": 70,
    "Powerslide Arise Marathon Skates": 70,
    "Doop Urban 100 Skates": 900000,
    "Doop Urban 90 Skates": 900000,
    "Powerslide Storm Meteor 80 Skates": 70,
    "Powerslide Pheme Leo 100 Skates": 900000,
    "Powerslide XC Trainer 150 Skates": 900000,
    "Powerslide Accel Race Reflective 125 Skates": 900000,
    "Powerslide Phuzion Argon Grey 90 Skates": 70,
    "Powerslide Swell Stellar Road 125 Skates": 70,
    "Powerslide HC EVO Pro 110 Skates": 70,
    "Powerslide Outback 150 SUV Frame": 2000
  }
}